naspy/__init__.py
naspy/dataculestream.py
naspy/datom.py
naspy/datom_index.py
naspy/io.py
naspy/scanner.py
naspy-1.0.0.dist-info/licenses/LICENSE
naspy-1.0.0.dist-info/METADATA
naspy-1.0.0.dist-info/WHEEL
naspy-1.0.0.dist-info/top_level.txt
naspy-1.0.0.dist-info/RECORD
