Metadata-Version: 2.4
Name: naspy
Version: 1.0.0
Summary: A lightweight memory protocol inspired by cognitive structure
Author-email: Beelito <beelito.dev@gmail.com>
License: MIT
Project-URL: Homepage, https://github.com/beelito/naspy
Requires-Python: >=3.8
License-File: LICENSE
Dynamic: license-file
